rtl/wr_ptr.sv
`timescale 1ns / 1ps

module wr_ptr #(parameter ADDR_WIDTH = 4)(      //four bit adressing to handle 16 bits
    input logic wr_clk,
    input logic wr_rst,
    input logic wr_en,
    input logic full,
    output logic [ADDR_WIDTH:0] b_wr_ptr,     //using addr_width + 1 to handle full logic
    output logic [ADDR_WIDTH:0] gr_wr_ptr
    );

always_ff @(posedge wr_clk or negedge wr_rst) begin
    if (!wr_rst) begin
        b_wr_ptr <= 0;
    end
    else if (wr_en && !full) begin              //logical operator used for comparing than arithmetic which multiplies
        b_wr_ptr <= b_wr_ptr + 1;
    end
end
assign gr_wr_ptr = (b_wr_ptr >> 1) ^ b_wr_ptr;          //converting to btog using right shift and XOR operations
endmodule

tb/wr_ptr_tb.sv
`timescale 1ns / 1ps

module wr_ptr_tb();
parameter ADDR_WIDTH = 4;
logic wr_clk;
logic wr_rst;
logic wr_en;
logic full;
logic [ADDR_WIDTH-1:0] b_wr_ptr;
logic [ADDR_WIDTH-1:0] gr_wr_ptr;

wr_ptr #(.ADDR_WIDTH(ADDR_WIDTH)) dut (
    .wr_clk(wr_clk),
    .wr_rst(wr_rst),
    .wr_en(wr_en),
    .full(full),
    .b_wr_ptr(b_wr_ptr),
    .gr_wr_ptr(gr_wr_ptr)
);

always #5 wr_clk = ~wr_clk;

initial begin
    $dumpfile("sim/wr_ptr/wr_ptr.vcd");
    $dumpvars(0,wr_ptr_tb);
    wr_clk = 0;
    wr_rst = 0;
    wr_en  = 0;
    full   = 0;

    #12;
    wr_rst = 1;

    repeat (5) begin
        wr_en = 1;
        full  = 0;
        #10;
    end

    wr_en = 0;
    #20;

    full = 1;
    wr_en = 1;
    #30;

    full = 0;
    wr_en = 1;
    #30;

    $finish;
end

endmodule

sim/wr_ptr/wr_ptr.vcd
$date
	Thu May  7 10:52:13 2026
$end
$version
	Icarus Verilog
$end
$timescale
	1ps
$end
$scope module wr_ptr_tb $end
$var wire 4 ! gr_wr_ptr [3:0] $end
$var wire 4 " b_wr_ptr [3:0] $end
$var parameter 32 # ADDR_WIDTH $end
$var reg 1 $ full $end
$var reg 1 % wr_clk $end
$var reg 1 & wr_en $end
$var reg 1 ' wr_rst $end
$scope module dut $end
$var wire 1 $ full $end
$var wire 5 ( gr_wr_ptr [4:0] $end
$var wire 1 % wr_clk $end
$var wire 1 & wr_en $end
$var wire 1 ' wr_rst $end
$var parameter 32 ) ADDR_WIDTH $end
$var reg 5 * b_wr_ptr [4:0] $end
$upscope $end
$upscope $end
$enddefinitions $end
$comment Show the parameter values. $end
$dumpall
b100 )
b100 #
$end
#0
$dumpvars
b0 *
b0 (
0'
0&
0%
0$
b0 "
b0 !
$end
#5000
1%
#10000
0%
#12000
1&
1'
#15000
b1 !
b1 (
b1 "
b1 *
1%
#20000
0%
#25000
b11 !
b11 (
b10 "
b10 *
1%
#30000
0%
#35000
b10 !
b10 (
b11 "
b11 *
1%
#40000
0%
#45000
b110 !
b110 (
b100 "
b100 *
1%
#50000
0%
#55000
b111 !
b111 (
b101 "
b101 *
1%
#60000
0%
#62000
0&
#65000
1%
#70000
0%
#75000
1%
#80000
0%
#82000
1&
1$
#85000
1%
#90000
0%
#95000
1%
#100000
0%
#105000
1%
#110000
0%
#112000
0$
#115000
b101 !
b101 (
b110 "
b110 *
1%
#120000
0%
#125000
b100 !
b100 (
b111 "
b111 *
1%
#130000
0%
#135000
b1100 !
b1100 (
b1000 "
b1000 *
1%
