rtl/rd_ptr.sv
`timescale 1ns / 1ps
module rd_ptr #(parameter ADDR_WIDTH = 4)(
    input logic rd_clk,
    input logic rd_rst_n,
    input logic rd_en,
    input logic empty,
    output logic [ADDR_WIDTH:0] b_rd_ptr,
    output logic [ADDR_WIDTH:0] gr_rd_ptr
);

always_ff @(posedge rd_clk or negedge rd_rst_n) begin
    if (!rd_rst_n) begin
        b_rd_ptr <= 0;
    end
    else if (rd_en && !empty) begin
        b_rd_ptr <= b_rd_ptr + 1;
    end
end
assign gr_rd_ptr = (b_rd_ptr >> 1) ^ b_rd_ptr;
endmodule

tb/rd_ptr_tb.sv
`timescale 1ns / 1ps
`timescale 1ns / 1ps

module rd_ptr_tb;
parameter ADDR_WIDTH = 4;
logic clk;
logic rd_rst_n;
logic rd_en;
logic empty;

logic [ADDR_WIDTH:0] b_rd_ptr;
logic [ADDR_WIDTH:0] gr_rd_ptr;

rd_ptr #(.ADDR_WIDTH(ADDR_WIDTH)) UUT(
    .rd_clk(clk),
    .rd_rst_n(rd_rst_n),
    .rd_en(rd_en),
    .empty(empty),
    .b_rd_ptr(b_rd_ptr),
    .gr_rd_ptr(gr_rd_ptr)
);

always #5 clk = ~clk;
initial begin
    $dumpfile("sim/rd_ptr/rd_ptr.vcd");
    $dumpvars(0,rd_ptr_tb);
    clk = 0;
    rd_rst_n = 0;
    rd_en = 0;
    empty = 1;
    #12 rd_rst_n = 1;
    #10 rd_en = 1;
    empty = 1;
    #20 empty = 0;
    #10 rd_en = 1;
    #40 rd_en = 1;
    #40 rd_en = 1;
    #20 rd_en = 0;

    $finish;
end

endmodule

sim/rd_ptr/rd_ptr.vcd
$date
	Thu May  7 11:54:50 2026
$end
$version
	Icarus Verilog
$end
$timescale
	1ps
$end
$scope module rd_ptr_tb $end
$var wire 5 ! gr_rd_ptr [4:0] $end
$var wire 5 " b_rd_ptr [4:0] $end
$var parameter 32 # ADDR_WIDTH $end
$var reg 1 $ clk $end
$var reg 1 % empty $end
$var reg 1 & rd_en $end
$var reg 1 ' rd_rst_n $end
$scope module UUT $end
$var wire 1 % empty $end
$var wire 5 ( gr_rd_ptr [4:0] $end
$var wire 1 $ rd_clk $end
$var wire 1 & rd_en $end
$var wire 1 ' rd_rst_n $end
$var parameter 32 ) ADDR_WIDTH $end
$var reg 5 * b_rd_ptr [4:0] $end
$upscope $end
$upscope $end
$enddefinitions $end
$comment Show the parameter values. $end
$dumpall
b100 )
b100 #
$end
#0
$dumpvars
b0 *
b0 (
0'
0&
1%
0$
b0 "
b0 !
$end
#5000
1$
#10000
0$
#12000
1'
#15000
1$
#20000
0$
#22000
1&
#25000
1$
#30000
0$
#35000
1$
#40000
0$
#42000
0%
#45000
b1 !
b1 (
b1 "
b1 *
1$
#50000
0$
#55000
b11 !
b11 (
b10 "
b10 *
1$
#60000
0$
#65000
b10 !
b10 (
b11 "
b11 *
1$
#70000
0$
#75000
b110 !
b110 (
b100 "
b100 *
1$
#80000
0$
#85000
b111 !
b111 (
b101 "
b101 *
1$
#90000
0$
#95000
b101 !
b101 (
b110 "
b110 *
1$
#100000
0$
#105000
b100 !
b100 (
b111 "
b111 *
1$
#110000
0$
#115000
b1100 !
b1100 (
b1000 "
b1000 *
1$
#120000
0$
#125000
b1101 !
b1101 (
b1001 "
b1001 *
1$
#130000
0$
#135000
b1111 !
b1111 (
b1010 "
b1010 *
1$
#140000
0$
#145000
b1110 !
b1110 (
b1011 "
b1011 *
1$
#150000
0$
#152000
0&
