blocks/ff_sync/ff_sync.sv
`timescale 1ns / 1ps
module ff_sync #(parameter WIDTH = 4)(
    input logic clk,
    input logic rst_n,      //active low reset (resets when rst_n_n is 0)
    input logic [WIDTH-1:0] din,
    output logic [WIDTH-1:0] dout
);
logic [WIDTH-1:0]q1;
always_ff @(posedge clk or negedge rst_n) begin
    if (!rst_n) begin
        q1 <= 0;
    end
    else begin
        q1 <= din;
    end
end

always_ff @(posedge clk or negedge rst_n) begin
    if (!rst_n) begin
        dout <= 0;
    end
    else begin
        dout <= q1;
    end
end
endmodule

blocks/ff_sync/2ff_sync_tb.sv
`timescale 1ps/1ps
module ff_sync_test();
parameter WIDTH = 4;
logic clk;
logic rst_n;
logic [WIDTH-1:0] din;
logic [WIDTH-1:0] dout;

ff_sync #(.WIDTH(WIDTH)) UUT (
    .clk(clk),
    .rst_n(rst_n),
    .din(din),
    .dout(dout)
);

initial clk = 0;
always #5 clk = ~clk;

initial begin
    rst_n = 0;
    din = 4'b0;
    $dumpfile("sim.vcd");
    $dumpvars(0,ff_sync_test);
    $monitor("Time = %t | clk = %b | rst_n = %b | din = %b | q1 = %b | dout = %b", $time, clk, rst_n, UUT.q1, din, dout);
    #12
    rst_n = 1;
    #3
    din = 4'b0001; #10
    din = 4'b0010; #10
    din = 4'b0011; #10
    din = 4'b0100; #10
    din = 4'b0101; #10
    din = 4'b0110; #10
    din = 4'b0111; #10
    #20 $finish;
end

endmodule

blocks/ff_sync/sim.vcd
$date
	Sun Apr 19 10:53:27 2026
$end
$version
	Icarus Verilog
$end
$timescale
	1ps
$end
$scope module ff_sync_test $end
$var wire 4 ! dout [3:0] $end
$var parameter 32 " WIDTH $end
$var reg 1 # clk $end
$var reg 4 $ din [3:0] $end
$var reg 1 % rst_n $end
$scope module UUT $end
$var wire 1 # clk $end
$var wire 4 & din [3:0] $end
$var wire 1 % rst_n $end
$var parameter 32 ' WIDTH $end
$var reg 4 ( dout [3:0] $end
$var reg 4 ) q1 [3:0] $end
$upscope $end
$upscope $end
$enddefinitions $end
$comment Show the parameter values. $end
$dumpall
b100 '
b100 "
$end
#0
$dumpvars
b0 )
b0 (
b0 &
0%
b0 $
0#
b0 !
$end
#5
1#
#10
0#
#12
1%
#15
b1 )
b1 $
b1 &
1#
#20
0#
#25
b1 !
b1 (
b10 )
1#
b10 $
b10 &
#30
0#
#35
b11 )
b10 !
b10 (
1#
b11 $
b11 &
#40
0#
#45
b11 !
b11 (
b100 )
1#
b100 $
b100 &
#50
0#
#55
b101 )
b100 !
b100 (
1#
b101 $
b101 &
#60
0#
#65
b101 !
b101 (
b110 )
1#
b110 $
b110 &
#70
0#
#75
b111 )
b110 !
b110 (
1#
b111 $
b111 &
#80
0#
#85
b111 !
b111 (
1#
