blocks/ff_sync/ff_sync.sv
`timescale 1ns / 1ps
module ff_sync #(parameter WIDTH = 4)(
    input logic clk,
    input logic rst_n,      //active low reset (resets when rst_n_n is 0)
    input logic [WIDTH-1:0] din,
    output logic [WIDTH-1:0] dout
);
logic [WIDTH-1:0]q1;
always_ff @(posedge clk or negedge rst_n) begin
    if (!rst_n) begin
        q1 <= 0;
    end
    else begin
        q1 <= din;
    end
end

always_ff @(posedge clk or negedge rst_n) begin
    if (!rst_n) begin
        dout <= 0;
    end
    else begin
        dout <= q1;
    end
end
endmodule

tb/ff_sync_tb.sv
`timescale 1ns / 1ps
module ff_sync_tb();
parameter  WIDTH = 4;
logic clk;
logic rst_n;
logic [WIDTH-1:0]din;
logic [WIDTH-1:0]dout;

ff_sync #(.WIDTH(WIDTH))UUT(
    .clk(clk),
    .rst_n(rst_n),
    .din(din),
    .dout(dout)
);

always #5 clk = ~clk;

initial begin
    $dumpfile("sim/ff_sync/output.vcd");
    $dumpvars(0,ff_sync_tb);
    clk = 0;
    rst_n = 0;
    din = 0;

    #10 rst_n = 1;

    #10 din = 4'b0001;
    #40 din = 4'b0011;
    #40 din = 4'b1010;
    #40 din = 4'b0101;

    $finish;
end

endmodule

sim/ff_sync/output.vcd
$date
	Thu May  7 10:07:36 2026
$end
$version
	Icarus Verilog
$end
$timescale
	1ps
$end
$scope module ff_sync_tb $end
$var wire 4 ! dout [3:0] $end
$var parameter 32 " WIDTH $end
$var reg 1 # clk $end
$var reg 4 $ din [3:0] $end
$var reg 1 % rst_n $end
$scope module UUT $end
$var wire 1 # clk $end
$var wire 4 & din [3:0] $end
$var wire 1 % rst_n $end
$var parameter 32 ' WIDTH $end
$var reg 4 ( dout [3:0] $end
$var reg 4 ) q1 [3:0] $end
$upscope $end
$upscope $end
$enddefinitions $end
$comment Show the parameter values. $end
$dumpall
b100 '
b100 "
$end
#0
$dumpvars
b0 )
b0 (
b0 &
0%
b0 $
0#
b0 !
$end
#5000
1#
#10000
0#
1%
#15000
1#
#20000
0#
b1 $
b1 &
#25000
b1 )
1#
#30000
0#
#35000
b1 !
b1 (
1#
#40000
0#
#45000
1#
#50000
0#
#55000
1#
#60000
0#
b11 $
b11 &
#65000
b11 )
1#
#70000
0#
#75000
b11 !
b11 (
1#
#80000
0#
#85000
1#
#90000
0#
#95000
1#
#100000
0#
b1010 $
b1010 &
#105000
b1010 )
1#
#110000
0#
#115000
b1010 !
b1010 (
1#
#120000
0#
#125000
1#
#130000
0#
#135000
1#
#140000
0#
b101 $
b101 &
